{
  "Category": "Juguetes",
  "SubCategory": "Otros",
  "Images": [
    "/images/products/tableta-de-escritura-tekfun-1.webp",
    "/images/products/tableta-de-escritura-tekfun-2.webp",
    "/images/products/tableta-de-escritura-tekfun-3.webp",
    "/images/products/tableta-de-escritura-tekfun-4.webp",
    "/images/products/tableta-de-escritura-tekfun-5.webp"
  ],
  "Description": "Última tecnología LCD sensible a la presión\n\nPantalla borrable\n\nPantalla colorida de 25cm, proporcionando colores vivos del arco iris\n\nDibuja líneas coloridas de diferentes grosores dependiendo de la fuerza de presión con un lápiz\n\nFomenta las habilidades de escritura temprana y promovue la coordinación ojo-mano\n\nEdad recomendada por el fabricante: +3 Años",
  "Price": 15.00,
  "Features": [
    "LCD",
    "25cm",
    "Lápiz óptico",
    "+3 Años",
    "Niña",
    "Niño"
  ],
  "Date": "2024-01-22T14:34:53.9979365-05:00",
  "Update": "2024-02-09T16:44:51.1911052-05:00",
  "Label": "Tableta de Escritura TEKFUN"
}